savingfigures/__init__.py
savingfigures/savingfigures.py
savingfigures-1.0.4.dist-info/LICENSE
savingfigures-1.0.4.dist-info/METADATA
savingfigures-1.0.4.dist-info/WHEEL
savingfigures-1.0.4.dist-info/top_level.txt
savingfigures-1.0.4.dist-info/RECORD
